Metadata-Version: 1.0
Name: django-fe-core
Version: 0.3.0
Summary: UNKNOWN
Home-page: https://github.com/fernandoe/django-fe-core
Author: Fernando Espíndola
Author-email: fer.esp@gmail.com
License: MIT
Platform: UNKNOWN
